ja_text_cleaner/__init__.py
ja_text_cleaner/abc.py
ja_text_cleaner/mappings.py
ja_text_cleaner/name.py
ja_text_cleaner/normalizer.py
ja_text_cleaner/processor.py
ja_text_cleaner/restapi.py
ja_text_cleaner/tokenizer.py
ja_text_cleaner-0.0.1.dist-info/WHEEL
ja_text_cleaner-0.0.1.dist-info/METADATA
ja_text_cleaner-0.0.1.dist-info/RECORD
