Metadata-Version: 2.1
Name: ja-text-cleaner
Version: 0.0.1
Summary: 日本語のための日本語変換ライブラリ
Home-page: https://github.com/sasano8/ja_text_cleaner
License: MIT
Author: sasano8
Author-email: y-sasahara@ys-method.com
Requires-Python: >=3.8,<4.0
Classifier: License :: OSI Approved :: MIT License
Classifier: Programming Language :: Python :: 3
Classifier: Programming Language :: Python :: 3.8
Requires-Dist: jaconv (>=0.3,<0.4)
Requires-Dist: mojimoji (>=0.0.11,<0.0.12)
Requires-Dist: romkan (>=0.2.1,<0.3.0)
Requires-Dist: sudachipy (>=0.5.2,<0.6.0)
Project-URL: Repository, https://github.com/sasano8/ja_text_cleaner
